virgui/__init__.py
virgui/action_runner.py
virgui/check_version.py
virgui/component.py
virgui/console.py
virgui/graph.py
virgui/kat_log.py
virgui/katscript_viewer.py
virgui/main.py
virgui/model_layout.py
virgui/parameter_table.py
virgui/parse_layout.py
virgui/plotting.py
virgui/scientific_spinbox.py
virgui/version.py
virgui/assets/2-port.svg
virgui/assets/miron.png
virgui/layouts/cavity/layout.kat
virgui/layouts/cavity/layout.svg
virgui/layouts/virgo_test/layout.kat
virgui/layouts/virgo_test/layout.svg
virgui-0.1.15.dist-info/METADATA
virgui-0.1.15.dist-info/WHEEL
virgui-0.1.15.dist-info/entry_points.txt
virgui-0.1.15.dist-info/top_level.txt
virgui-0.1.15.dist-info/RECORD
