Metadata-Version: 2.4
Name: virgui
Version: 0.1.15
Summary: Prototype for the Virgo control room GUI
Author-email: Miron van der Kolk <mkolk@nikhef.nl>
Classifier: Programming Language :: Python :: 3
Classifier: License :: OSI Approved :: MIT License
Classifier: Operating System :: OS Independent
Requires-Python: >=3.8
Requires-Dist: pyside6
Requires-Dist: finesse
Requires-Dist: pygments
Requires-Dist: lxml
Requires-Dist: ipython<9
Requires-Dist: pygraphviz
Provides-Extra: test
Requires-Dist: pytest; extra == "test"
Provides-Extra: lint
Requires-Dist: ruff; extra == "lint"
Requires-Dist: pre-commit; extra == "lint"
Requires-Dist: tox; extra == "lint"
